solTg/ReportBuilder.py
solTg/RunAll.py
solTg/SolParser.py
solTg/SolidityTestGen.py
solTg/TestWrapper.py
solTg/Utils.py
solTg/__init__.py
soltg-0.2.1.data/data/deps/docker_solcmc_updated
soltg-0.2.1.data/data/deps/run_solcmc
soltg-0.2.1.data/data/deps/tgnonlin
soltg-0.2.1.data/data/deps/tgnonlin_linux
soltg-0.2.1.dist-info/METADATA
soltg-0.2.1.dist-info/WHEEL
soltg-0.2.1.dist-info/entry_points.txt
soltg-0.2.1.dist-info/top_level.txt
soltg-0.2.1.dist-info/RECORD
